lammpsinputbuilder/__init__.py
lammpsinputbuilder/base.py
lammpsinputbuilder/extensions.py
lammpsinputbuilder/fileio.py
lammpsinputbuilder/group.py
lammpsinputbuilder/instructions.py
lammpsinputbuilder/integrator.py
lammpsinputbuilder/quantities.py
lammpsinputbuilder/section.py
lammpsinputbuilder/typedmolecule.py
lammpsinputbuilder/types.py
lammpsinputbuilder/units.txt
lammpsinputbuilder/version.py
lammpsinputbuilder/workflow_builder.py
lammpsinputbuilder/loader/__init__.py
lammpsinputbuilder/loader/extension_loader.py
lammpsinputbuilder/loader/fileio_loader.py
lammpsinputbuilder/loader/group_loader.py
lammpsinputbuilder/loader/instruction_loader.py
lammpsinputbuilder/loader/integrator_loader.py
lammpsinputbuilder/loader/section_loader.py
lammpsinputbuilder/loader/typedmolecule_loader.py
lammpsinputbuilder/model/__init__.py
lammpsinputbuilder/model/base_model.py
lammpsinputbuilder/model/extension_model.py
lammpsinputbuilder/model/fileio_model.py
lammpsinputbuilder/model/group_model.py
lammpsinputbuilder/model/instruction_model.py
lammpsinputbuilder/model/integrator_model.py
lammpsinputbuilder/model/quantity_model.py
lammpsinputbuilder/model/section_model.py
lammpsinputbuilder/model/template_model.py
lammpsinputbuilder/model/typedmolecule_model.py
lammpsinputbuilder/model/workflow_builder_model.py
lammpsinputbuilder/templates/__init__.py
lammpsinputbuilder/templates/minimize_template.py
lammpsinputbuilder/templates/template_section.py
lammpsinputbuilder/utility/__init__.py
lammpsinputbuilder/utility/model_to_data.py
lammpsinputbuilder/utility/string_utils.py
lammpsinputbuilder-0.0.8.dist-info/LICENSE
lammpsinputbuilder-0.0.8.dist-info/METADATA
lammpsinputbuilder-0.0.8.dist-info/WHEEL
lammpsinputbuilder-0.0.8.dist-info/top_level.txt
lammpsinputbuilder-0.0.8.dist-info/RECORD
