Metadata-Version: 2.1
Name: lammpsinputbuilder
Version: 0.0.8
Summary: LammpsInputBuilder (or LIB) is a Python library designed to generate Lammps inputs from a molecular model, a forcefield, and a high level definition of a simulation workflow.
Author: Matthieu Dreher
Author-email: Matthieu Dreher <dreher.matthieu@gmail.com>
Maintainer: Matthieu Dreher
Maintainer-email: dreher.matthieu@gmail.com
License: MIT License
Project-URL: Homepage, https://github.com/madreher/LammpsInputBuilder
Project-URL: Issues, https://github.com/madreher/LammpsInputBuilder/issues
Classifier: Programming Language :: Python :: 3
Classifier: License :: OSI Approved :: MIT License
Classifier: Operating System :: OS Independent
Requires-Python: >=3.9
License-File: LICENSE
Requires-Dist: ase
Requires-Dist: pint
Requires-Dist: lammps-logfile
Requires-Dist: matplotlib
Requires-Dist: pylint
Requires-Dist: pydantic
